odoo/addons/base_external_api/README.rst
odoo/addons/base_external_api/__init__.py
odoo/addons/base_external_api/__manifest__.py
odoo/addons/base_external_api/demo/external_api_config.xml
odoo/addons/base_external_api/i18n/es.po
odoo/addons/base_external_api/models/__init__.py
odoo/addons/base_external_api/models/external_api_config.py
odoo/addons/base_external_api/models/external_api_log.py
odoo/addons/base_external_api/readme/CONTRIBUTORS.md
odoo/addons/base_external_api/readme/DESCRIPTION.md
odoo/addons/base_external_api/readme/ROADMAP.md
odoo/addons/base_external_api/readme/USAGE.md
odoo/addons/base_external_api/security/ir.model.access.csv
odoo/addons/base_external_api/static/description/icon.png
odoo/addons/base_external_api/static/description/index.html
odoo/addons/base_external_api/tests/__init__.py
odoo/addons/base_external_api/tests/test_base_external_api.py
odoo/addons/base_external_api/views/external_api_config_views.xml
odoo/addons/base_external_api/views/external_api_log_views.xml
odoo/addons/base_external_api/views/external_api_menus.xml
odoo_addon_base_external_api-17.0.1.2.0.dist-info/METADATA
odoo_addon_base_external_api-17.0.1.2.0.dist-info/WHEEL
odoo_addon_base_external_api-17.0.1.2.0.dist-info/top_level.txt
odoo_addon_base_external_api-17.0.1.2.0.dist-info/RECORD
