Metadata-Version: 2.1
Name: odoo-addon-base_external_api
Version: 17.0.1.2.0
Requires-Python: >=3.10
Requires-Dist: odoo-addon-queue_job>=17.0dev,<17.1dev
Requires-Dist: odoo>=17.0a,<17.1dev
Requires-Dist: requests
Summary: Tools to manage external api connections.
Home-page: https://github.com/sygel-technology/sy-server-backend
License: AGPL-3
Author: Sygel, Odoo Community Association (OCA)
Author-email: support@odoo-community.org
Classifier: Programming Language :: Python
Classifier: Framework :: Odoo
Classifier: Framework :: Odoo :: 17.0
Classifier: License :: OSI Approved :: GNU Affero General Public License v3
